apexpy-2.0.2.dist-info/METADATA
apexpy-2.0.2.dist-info/WHEEL
apexpy-2.0.2.dist-info/LICENSE
apexpy/fortranapex.cpython-310-darwin.so
apexpy/__init__.py
apexpy/__main__.py
apexpy/apex.py
apexpy/apexsh.dat
apexpy/helpers.py
apexpy/igrf13coeffs.txt
apexpy-2.0.2.dist-info/RECORD
