Metadata-Version: 2.1
Name: apexpy
Version: 2.0.2
Summary: A Python wrapper for Apex coordinates
Keywords: apex,modified apex,quasi-dipole,quasi dipole,coordinates,magnetic coordinates,mlt,magnetic local time,conversion,converting
Maintainer-Email: Angeline Burrell <angeline.g.burrell.civ@us.navy.mil>
License: The MIT License (MIT)
Classifier: Development Status :: 5 - Production/Stable
Classifier: Intended Audience :: Science/Research
Classifier: License :: OSI Approved :: MIT License
Classifier: Programming Language :: Fortran
Classifier: Programming Language :: Python
Classifier: Programming Language :: Python :: 3
Classifier: Programming Language :: Python :: 3.9
Classifier: Programming Language :: Python :: 3.10
Classifier: Programming Language :: Python :: 3.11
Classifier: Programming Language :: Python :: Implementation :: CPython
Classifier: Topic :: Software Development :: Libraries
Classifier: Topic :: Scientific/Engineering :: Physics
Classifier: Topic :: Utilities
Classifier: Operating System :: Microsoft :: Windows
Classifier: Operating System :: POSIX :: Linux
Classifier: Operating System :: POSIX
Classifier: Operating System :: Unix
Classifier: Operating System :: MacOS
Project-URL: source, https://github.com/aburrell/apexpy
Project-URL: documentation, https://apexpy.readthedocs.io/en/latest/
Project-URL: tracker, https://github.com/aburrell/apexpy/issues
Project-URL: download, https://github.com/aburrell/apexpy/releases
Requires-Python: <3.12,>=3.9
Requires-Dist: numpy<2,>=1.19.5
Provides-Extra: test
Requires-Dist: coverage; extra == "test"
Requires-Dist: flake8; extra == "test"
Requires-Dist: pytest; extra == "test"
Requires-Dist: pytest-cov; extra == "test"
Requires-Dist: pytest-xdist; extra == "test"
Provides-Extra: doc
Requires-Dist: sphinx>=1.3; extra == "doc"
Requires-Dist: sphinx-rtd-theme; extra == "doc"
